Metadata-Version: 2.4
Name: pyboot-commons-redis
Version: 1.3.3
Summary: Pyboot-commons-redis is an open-source Pyboot utility package that A foundational Redis utils package designed for general-purpose tooling.
Author-email: joinsunsoft <793875613@qq.com>
Maintainer-email: joinsunsoft <inthirties.liu@hotmail.com>
License-Expression: Apache-2.0
Project-URL: Homepage, https://gitee.com/pyboot/commons-redis
Project-URL: Repository, https://gitee.com/pyboot/commons-redis
Project-URL: Issues, https://gitee.com/pyboot/commons-redis
Keywords: web,framework,cli,springboot,fastapi,redis
Classifier: Development Status :: 4 - Beta
Classifier: Intended Audience :: Developers
Classifier: Operating System :: OS Independent
Classifier: Programming Language :: Python :: 3
Classifier: Programming Language :: Python :: 3.8
Classifier: Programming Language :: Python :: 3.9
Classifier: Programming Language :: Python :: 3.10
Classifier: Programming Language :: Python :: 3.11
Classifier: Programming Language :: Python :: 3.12
Classifier: Topic :: Software Development :: Libraries :: Application Frameworks
Requires-Python: >=3.12.10
License-File: LICENSE
Requires-Dist: pyboot-commons-utils
Requires-Dist: redis==6.2.0
Dynamic: license-file
